evolution/__init__.py
evolution/client.py
evolution/exceptions.py
evolution/models/__init__.py
evolution/models/call.py
evolution/models/chat.py
evolution/models/group.py
evolution/models/instance.py
evolution/models/label.py
evolution/models/message.py
evolution/models/presence.py
evolution/models/profile.py
evolution/services/__init__.py
evolution/services/call.py
evolution/services/chat.py
evolution/services/group.py
evolution/services/instance.py
evolution/services/instance_operations.py
evolution/services/label.py
evolution/services/message.py
evolution/services/profile.py
evolutionapi/__init__.py
evolutionapi/client.py
evolutionapi/exceptions.py
evolutionapi/models/__init__.py
evolutionapi/models/call.py
evolutionapi/models/chat.py
evolutionapi/models/group.py
evolutionapi/models/instance.py
evolutionapi/models/label.py
evolutionapi/models/message.py
evolutionapi/models/presence.py
evolutionapi/models/profile.py
evolutionapi/models/websocket.py
evolutionapi/services/__init__.py
evolutionapi/services/call.py
evolutionapi/services/chat.py
evolutionapi/services/group.py
evolutionapi/services/instance.py
evolutionapi/services/instance_operations.py
evolutionapi/services/label.py
evolutionapi/services/message.py
evolutionapi/services/profile.py
evolutionapi/services/websocket.py
evolutionapi_marciobkn-0.1.1.dist-info/METADATA
evolutionapi_marciobkn-0.1.1.dist-info/WHEEL
evolutionapi_marciobkn-0.1.1.dist-info/top_level.txt
evolutionapi_marciobkn-0.1.1.dist-info/RECORD
