Metadata-Version: 2.4
Name: evolutionapi-marciobkn
Version: 0.1.1
Summary: Client Python para a API Evolution
Author: Davidson Gomes
Author-email: contato@agenciadgcode.com
Requires-Python: >=3.6
Requires-Dist: requests>=2.25.1
Requires-Dist: requests_toolbelt>=1.0.0
Requires-Dist: python-socketio>=5.11.1
Dynamic: author
Dynamic: author-email
Dynamic: requires-dist
Dynamic: requires-python
Dynamic: summary
